ai_sandbox/__init__.py
ai_sandbox/executor.py
ai_sandbox/security.py
uv_ai_sandbox-0.1.0.dist-info/LICENSE
uv_ai_sandbox-0.1.0.dist-info/METADATA
uv_ai_sandbox-0.1.0.dist-info/WHEEL
uv_ai_sandbox-0.1.0.dist-info/top_level.txt
uv_ai_sandbox-0.1.0.dist-info/RECORD
