Metadata-Version: 2.2
Name: uv-ai-sandbox
Version: 0.1.0
Summary: Sandboxed environment for running AI models with strict security boundaries
Author: AI Sandbox Team
License: MIT
Project-URL: Homepage, https://github.com/ngmisl/uv-ai-sandbox
Project-URL: Bug Tracker, https://github.com/ngmisl/uv-ai-sandbox/issues
Classifier: Development Status :: 4 - Beta
Classifier: Intended Audience :: Developers
Classifier: License :: OSI Approved :: MIT License
Classifier: Programming Language :: Python :: 3
Classifier: Programming Language :: Python :: 3.12
Classifier: Topic :: Security
Classifier: Topic :: Software Development :: Libraries :: Python Modules
Requires-Python: >=3.12
License-File: LICENSE
Requires-Dist: restrictedpython>=8.0
Requires-Dist: pydantic>=2.0.0
Requires-Dist: pathvalidate>=3.0.0
Requires-Dist: pathlib2>=2.3.7
Requires-Dist: path>=17.1.0
Requires-Dist: psutil>=7.0.0
Provides-Extra: dev
Requires-Dist: pytest>=8.3.5; extra == "dev"
Requires-Dist: black>=25.1.0; extra == "dev"
Requires-Dist: bandit>=1.7.5; extra == "dev"
Requires-Dist: safety>=3.0.0; extra == "dev"
Requires-Dist: ruff>=0.9.10; extra == "dev"
Requires-Dist: build>=1.0.0; extra == "dev"
Requires-Dist: twine>=4.0.0; extra == "dev"
Provides-Extra: linux
Requires-Dist: python-prctl>=1.8.1; extra == "linux"
